profanity_sanitizer/__init__.py
profanity_sanitizer/ai_model_handler.py
profanity_sanitizer/data_loader.py
profanity_sanitizer/fuzzy_matcher.py
profanity_sanitizer/profanity_sanitizer.py
profanity_sanitizer/semantic_similarity_checker.py
profanity_sanitizer/data/allowed_words.json
profanity_sanitizer/data/banned_words.json
profanity_sanitizer/data/replacements.json
profanity_sanitizer/models/__init__.py
profanity_sanitizer/models/profanity_result.py
profanity_sanitizer-0.1.4.dist-info/METADATA
profanity_sanitizer-0.1.4.dist-info/WHEEL
profanity_sanitizer-0.1.4.dist-info/entry_points.txt
profanity_sanitizer-0.1.4.dist-info/licenses/LICENSE
profanity_sanitizer-0.1.4.dist-info/RECORD
