Metadata-Version: 2.3
Name: profanity-sanitizer
Version: 0.1.4
Summary: A profanity sanitizer with fuzzy matching, semantic similarity, and AI-based toxicity detection
Author: Martin Dostalik
License-Expression: MIT
License-File: LICENSE
Requires-Python: >=3.12
Requires-Dist: fuzzywuzzy==0.18.0
Requires-Dist: numpy<2.0.0,>=1.26.0
Requires-Dist: python-levenshtein
Requires-Dist: spacy==3.7.2
Requires-Dist: tensorflow==2.17.0
Requires-Dist: tf-keras
Requires-Dist: transformers==4.38.0
Provides-Extra: dev
Requires-Dist: pytest>=7.0; extra == 'dev'
